<?xml version="1.0" encoding="UTF-8"?>
<package xmlns="http://apple.com/itunes/importer" version="software5.2">
    <!-- This document was generated on Jan 29, 2015 9:06:44 AM for lioyufrj@gmail.com <lioyufrj@gmail.com>. -->
    <!-- NOTE: metadata_token is generated on lookup.  Modifying the value of this will result in an import error -->
    <metadata_token>1422551204778-05c9cfb2a97a0faded00b9efc430bea827461c575e7fe27ad8c1dbfe79b1332e</metadata_token>
    <provider>J5P786SDN2</provider>
    <team_id>J5P786SDN2</team_id>
    <software>
        <!--Apple ID: 917468380-->
        <vendor_id>com.tplioy.partyUp</vendor_id>
        <read_only_info>
            <read_only_value key="apple-id">917468380</read_only_value>
        </read_only_info>
        <software_metadata>
            <versions>
                <version string="1.1">
                    <locales>
                        <locale name="pt-BR">
                            <title>PartyUp</title>
                        </locale>
                    </locales>
                </version>
            </versions>
        </software_metadata>
    </software>
</package>
